generator3/__init__.py
generator3-0.1.0.dist-info/LICENSE
generator3-0.1.0.dist-info/METADATA
generator3-0.1.0.dist-info/WHEEL
generator3-0.1.0.dist-info/top_level.txt
generator3-0.1.0.dist-info/RECORD
