Metadata-Version: 2.1
Name: generator3
Version: 0.1.0
Summary: Parse Scratch's large project JSONs and convert them to scratchblocks notation
Home-page: https://github.com/themysticsavages/generator3
Author: themysticsavages
License: MIT
Platform: UNKNOWN
Classifier: Programming Language :: Python :: 3
Classifier: License :: OSI Approved :: MIT License
Classifier: Operating System :: OS Independent
Requires-Python: >=3.6
Requires-Dist: requests
Requires-Dist: flask
